hn_pwa_api/__init__.py
hn_pwa_api/api.py
hn_pwa_api/entry.py
hn_pwa_api/feed.py
hn_pwa_api/post.py
hn_pwa_api-0.1.1.dist-info/WHEEL
hn_pwa_api-0.1.1.dist-info/METADATA
hn_pwa_api-0.1.1.dist-info/RECORD
