Metadata-Version: 2.1
Name: hn-pwa-api
Version: 0.1.1
Summary: 
Author: flomk
Author-email: sudogitrekt@gmail.com
Requires-Python: >=3.7,<4.0
Classifier: Programming Language :: Python :: 3
Classifier: Programming Language :: Python :: 3.7
Classifier: Programming Language :: Python :: 3.8
Requires-Dist: requests (==2.22.0)
